{
  "N": 200,
  "m": 24,
  "A": [
    0,
    1,
    2,
    4,
    11,
    21,
    32,
    37,
    48,
    52,
    63,
    71,
    77,
    85,
    86,
    90,
    158,
    164,
    170,
    176,
    182,
    188,
    194,
    200
  ],
  "metrics": {
    "N": 200,
    "m": 24,
    "S": 276,
    "missing_count": 12,
    "peak": 8,
    "H3": 18,
    "H4": 6,
    "E": 568,
    "Emin": 428,
    "rho": 1.3271028037383177,
    "count_w1": 131,
    "count_w2": 39,
    "count_w3": 12,
    "count_w4": 3,
    "count_w5": 1,
    "count_w6plus": 2
  }
}